django_crud_manager/__init__.py
django_crud_manager/constants.py
django_crud_manager/exceptions.py
django_crud_manager/general_manager.py
django_crud_manager/manager.py
django_crud_manager/manager_base.py
django_crud_manager/models.py
django_crud_manager-0.10.0.dist-info/METADATA
django_crud_manager-0.10.0.dist-info/WHEEL
django_crud_manager-0.10.0.dist-info/top_level.txt
django_crud_manager-0.10.0.dist-info/RECORD
