Metadata-Version: 2.1
Name: django_crud_manager
Version: 0.10.0
Summary: Django Crud Manager
Home-page: https://github.com/sauditore/SARequest/
Author: Amir Pourjafari
Author-email: Amir Pourjafari <amir.pourjafari@gmail.com>
Project-URL: Homepage, https://github.com/sauditore/SARequest
Project-URL: Issues, https://github.com/sauditore/SARequest/issues
Classifier: Programming Language :: Python :: 3
Classifier: License :: OSI Approved :: MIT License
Classifier: Operating System :: OS Independent
Requires-Python: >=3.6
Requires-Dist: django
Requires-Dist: pydantic
Requires-Dist: khayyam
